ansibledocgen/__init__.py
ansibledocgen/cli.py
ansibledocgen/core/__init__.py
ansibledocgen/core/docgenyaml.py
ansibledocgen/formatter/__init__.py
ansibledocgen/formatter/formatter.py
ansibledocgen/formatter/templates/__init__.py
ansibledocgen/formatter/templates/markdown_host.j2
ansibledocgen/formatter/templates/markdown_playbook.j2
ansibledocgen/formatter/templates/markdown_role.j2
ansibledocgen/parser/__init__.py
ansibledocgen/parser/ansiblecfg.py
ansibledocgen/parser/dir.py
ansibledocgen/parser/hostvars.py
ansibledocgen/parser/playbook.py
ansibledocgen/parser/role.py
ansible_docgen-1.0.0.dist-info/LICENSE.md
ansible_docgen-1.0.0.dist-info/METADATA
ansible_docgen-1.0.0.dist-info/WHEEL
ansible_docgen-1.0.0.dist-info/entry_points.txt
ansible_docgen-1.0.0.dist-info/top_level.txt
ansible_docgen-1.0.0.dist-info/RECORD
