Metadata-Version: 2.1
Name: ansible-docgen
Version: 1.0.0
Summary: Generate Documentation from Annotated Ansible Playbooks and Roles
Home-page: https://github.com/starboarder2001/ansible-docgen
Author: David Whiteside
Author-email: david@davidwhiteside.com
License: MIT
Classifier: Environment :: Console
Classifier: Intended Audience :: Developers
Classifier: Intended Audience :: Information Technology
Classifier: Intended Audience :: System Administrators
Classifier: License :: OSI Approved :: MIT License
Classifier: Natural Language :: English
Classifier: Operating System :: POSIX
Classifier: Programming Language :: Python :: 3
Classifier: Programming Language :: Python :: 3.7
Classifier: Programming Language :: Python :: 3.8
Classifier: Programming Language :: Python :: 3.9
Classifier: Programming Language :: Python :: 3.10
Classifier: Programming Language :: Python :: 3.11
Classifier: Programming Language :: Python :: 3.12
Classifier: Programming Language :: Python :: 3 :: Only
Classifier: Topic :: System :: Installation/Setup
Classifier: Topic :: System :: Systems Administration
Classifier: Topic :: Utilities
Requires-Python: >=3.7
License-File: LICENSE.md
Requires-Dist: PyYAML
Requires-Dist: setuptools
Requires-Dist: jinja2
